rcdb_unpacker-0.3.1.dist-info/METADATA
rcdb_unpacker-0.3.1.dist-info/WHEEL
rcdb_unpacker/__init__.py
rcdb_unpacker/rcdb_unpacker.cpython-312-arm-linux-gnueabihf.so
rcdb_unpacker-0.3.1.dist-info/RECORD
