Metadata-Version: 2.3
Name: rcdb_unpacker
Version: 0.3.1
Classifier: Programming Language :: Rust
Classifier: Programming Language :: Python :: Implementation :: CPython
Classifier: Programming Language :: Python :: 3
Classifier: Programming Language :: Python :: 3.8
Classifier: Programming Language :: Python :: 3.9
Classifier: Programming Language :: Python :: 3.10
Classifier: Programming Language :: Python :: 3.11
Classifier: Programming Language :: Python :: 3.12
Requires-Dist: rebotics-sdk
Home-Page: https://retechlabs.com/
Author: Malik Sulaimanov <malik@retechlabs.com>
Author-email: Malik Sulaimanov <malik@retechlabs.com>
Requires-Python: >=3.8
